anonymization/Anonymization.py
anonymization/__init__.py
anonymization/anonymizers/__init__.py
anonymization/anonymizers/bankingAnonymizers.py
anonymization/anonymizers/dateAnonymizers.py
anonymization/anonymizers/dictionaryAnonymizers.py
anonymization/anonymizers/fileAnonymizers.py
anonymization/anonymizers/internetAnonymizers.py
anonymization/anonymizers/phoneNumberAnonymizers.py
anonymization/anonymizers/signatureAnonymizers.py
anonymization/anonymizers/spacyAnonymizers.py
anonymization/lib/__init__.py
anonymization/lib/diff_match_patch.py
anonymization-0.1.9.dist-info/LICENSE
anonymization-0.1.9.dist-info/METADATA
anonymization-0.1.9.dist-info/WHEEL
anonymization-0.1.9.dist-info/top_level.txt
anonymization-0.1.9.dist-info/RECORD
