Metadata-Version: 2.1
Name: anonymization
Version: 0.1.9
Summary: Text anonymization using Faker
Home-page: https://github.com/alterway/anonymization
Author: Alter Way R&D
Author-email: rnd@alterway.fr
License: MIT
Platform: UNKNOWN
Requires-Python: >=3.6
Requires-Dist: Faker (<2,>=1)
Provides-Extra: spacyanonymizers
Requires-Dist: spacy (<3,>=2) ; extra == 'spacyanonymizers'
